micktrace/__init__.py
micktrace/py.typed
micktrace/types.py
micktrace/config/__init__.py
micktrace/config/configuration.py
micktrace/core/__init__.py
micktrace/core/aggregator.py
micktrace/core/buffer.py
micktrace/core/context.py
micktrace/core/logger.py
micktrace/filters/__init__.py
micktrace/filters/filters.py
micktrace/filters/sampling.py
micktrace/formatters/__init__.py
micktrace/formatters/colorized.py
micktrace/formatters/ecs.py
micktrace/formatters/formatters.py
micktrace/formatters/opentelemetry.py
micktrace/handlers/__init__.py
micktrace/handlers/async_azure.py
micktrace/handlers/async_base.py
micktrace/handlers/async_cloudwatch.py
micktrace/handlers/async_gcp.py
micktrace/handlers/async_stackdriver.py
micktrace/handlers/azure.py
micktrace/handlers/buffered.py
micktrace/handlers/cloudwatch.py
micktrace/handlers/console.py
micktrace/handlers/datadog.py
micktrace/handlers/file.py
micktrace/handlers/gcp.py
micktrace/handlers/handlers.py
micktrace/handlers/rotating.py
micktrace/handlers/stackdriver.py
micktrace/utils/__init__.py
micktrace/utils/performance.py
micktrace-1.0.5.dist-info/licenses/LICENSE
micktrace-1.0.5.dist-info/METADATA
micktrace-1.0.5.dist-info/WHEEL
micktrace-1.0.5.dist-info/top_level.txt
micktrace-1.0.5.dist-info/RECORD
