Metadata-Version: 2.4
Name: micktrace
Version: 1.0.5
Summary: Modern Python logging library for production applications - async-native, structured logging, zero-config, cloud-ready with AWS/Azure/GCP integration, context propagation, and performance optimization
Home-page: https://github.com/ajayagrawalgit/MickTrace
Author: Ajay Agrawal
Author-email: Ajay Agrawal <ajayagrawalofficial@gmail.com>
Maintainer: Ajay Agrawal
Maintainer-email: Ajay Agrawal <ajayagrawalofficial@gmail.com>
License: MIT
Project-URL: Homepage, https://github.com/ajayagrawalgit/MickTrace
Project-URL: Repository, https://github.com/ajayagrawalgit/MickTrace
Project-URL: Documentation, https://github.com/ajayagrawalgit/MickTrace#readme
Project-URL: Bug Tracker, https://github.com/ajayagrawalgit/MickTrace/issues
Project-URL: Source Code, https://github.com/ajayagrawalgit/MickTrace
Project-URL: Author Profile, https://github.com/ajayagrawalgit
Project-URL: LinkedIn, https://www.linkedin.com/in/theajayagrawal/
Project-URL: Changelog, https://github.com/ajayagrawalgit/MickTrace/blob/main/CHANGELOG.md
Keywords: python logging,async logging,structured logging,json logging,cloud logging,aws cloudwatch,azure monitor,google cloud logging,datadog logging,observability,tracing,monitoring,performance logging,production logging,library logging,context propagation,correlation id,microservices logging,kubernetes logging,docker logging,elasticsearch logging,logfmt,python logger,async python,logging library,log management,application logging,system logging,enterprise logging
Classifier: Development Status :: 5 - Production/Stable
Classifier: Intended Audience :: Developers
Classifier: License :: OSI Approved :: MIT License
Classifier: Operating System :: OS Independent
Classifier: Programming Language :: Python :: 3
Classifier: Programming Language :: Python :: 3.8
Classifier: Programming Language :: Python :: 3.9
Classifier: Programming Language :: Python :: 3.10
Classifier: Programming Language :: Python :: 3.11
Classifier: Programming Language :: Python :: 3.12
Classifier: Programming Language :: Python :: 3.13
Classifier: Topic :: Software Development :: Libraries :: Python Modules
Classifier: Topic :: System :: Logging
Classifier: Topic :: Software Development :: Debuggers
Classifier: Typing :: Typed
Classifier: Environment :: Console
Classifier: Framework :: AsyncIO
Requires-Python: >=3.8
License-File: LICENSE
Requires-Dist: typing-extensions>=4.0.0; python_version < "3.11"
Provides-Extra: dev
Requires-Dist: pytest>=7.0; extra == "dev"
Requires-Dist: pytest-asyncio>=0.21.0; extra == "dev"
Requires-Dist: pytest-cov>=4.0; extra == "dev"
Requires-Dist: black>=22.0; extra == "dev"
Requires-Dist: mypy>=1.0; extra == "dev"
Requires-Dist: ruff>=0.1.0; extra == "dev"
Requires-Dist: isort>=5.0; extra == "dev"
Provides-Extra: aws
Requires-Dist: aioboto3>=11.3.0; extra == "aws"
Requires-Dist: botocore>=1.31.62; extra == "aws"
Provides-Extra: azure
Requires-Dist: azure-monitor-ingestion>=1.0.0b5; extra == "azure"
Requires-Dist: azure-core>=1.29.5; extra == "azure"
Provides-Extra: gcp
Requires-Dist: google-cloud-logging>=3.8.0; extra == "gcp"
Provides-Extra: cloud
Requires-Dist: micktrace[aws,azure,gcp]; extra == "cloud"
Provides-Extra: datadog
Requires-Dist: datadog>=0.44.0; extra == "datadog"
Requires-Dist: requests>=2.28.0; extra == "datadog"
Provides-Extra: newrelic
Requires-Dist: newrelic>=8.0.0; extra == "newrelic"
Provides-Extra: elastic
Requires-Dist: elasticsearch>=8.0.0; extra == "elastic"
Provides-Extra: prometheus
Requires-Dist: prometheus-client>=0.16.0; extra == "prometheus"
Provides-Extra: sentry
Requires-Dist: sentry-sdk>=1.0.0; extra == "sentry"
Provides-Extra: analytics
Requires-Dist: micktrace[datadog,elastic,newrelic,prometheus,sentry]; extra == "analytics"
Provides-Extra: performance
Requires-Dist: orjson>=3.8.0; extra == "performance"
Requires-Dist: msgpack>=1.0.0; extra == "performance"
Requires-Dist: lz4>=4.0.0; extra == "performance"
Provides-Extra: rich
Requires-Dist: rich>=13.0.0; extra == "rich"
Provides-Extra: opentelemetry
Requires-Dist: opentelemetry-api>=1.15.0; extra == "opentelemetry"
Requires-Dist: opentelemetry-sdk>=1.15.0; extra == "opentelemetry"
Provides-Extra: all
Requires-Dist: micktrace[analytics,cloud,dev,opentelemetry,performance,rich]; extra == "all"
Dynamic: license-file
